venue.S.HTML
law_dictionary/__init__.py
law_dictionary/_clique/__init__.py
law_dictionary/_clique/group/__init__.py
law_dictionary/_license/license.s.HTML
law_dictionary/_license/licenses/gpl-3.0-standalone.html
law_dictionary/_status/DB/records.json
law_dictionary/_status/status.proc.py
law_dictionary/dictionary_laws.s.HTML
law_dictionary/module.MD
law_dictionary/module.s.HTML
law_dictionary/status_1.py
law_dictionary/status_2.py
law_dictionary/status_3.py
law_dictionary/status_broken_1.py
law_dictionary/status_broken_2.py
law_dictionary-1.0.12.dist-info/METADATA
law_dictionary-1.0.12.dist-info/WHEEL
law_dictionary-1.0.12.dist-info/RECORD
