Metadata-Version: 2.1
Name: law_dictionary
Version: 1.0.12
Summary: JSON dictionary variable checks
License: GPL-3.0-only
Requires-Python: >=3.10,<4.0
Classifier: License :: OSI Approved :: GNU General Public License v3 (GPLv3)
Classifier: Programming Language :: Python :: 3
Classifier: Programming Language :: Python :: 3.10
Classifier: Programming Language :: Python :: 3.11
Classifier: Programming Language :: Python :: 3.12
Requires-Dist: biotech (>=1.0.3,<2.0.0)
Requires-Dist: click (>=8.1.7,<9.0.0)
Project-URL: GitLab, https://gitlab.com/offline-money/squash-1/law_dictionary
